dapr_agents_oas_adapter/__init__.py
dapr_agents_oas_adapter/async_loader.py
dapr_agents_oas_adapter/cache.py
dapr_agents_oas_adapter/converters/__init__.py
dapr_agents_oas_adapter/converters/agent.py
dapr_agents_oas_adapter/converters/base.py
dapr_agents_oas_adapter/converters/flow.py
dapr_agents_oas_adapter/converters/llm.py
dapr_agents_oas_adapter/converters/node.py
dapr_agents_oas_adapter/converters/tool.py
dapr_agents_oas_adapter/converters/workflow_helpers.py
dapr_agents_oas_adapter/exporter.py
dapr_agents_oas_adapter/loader.py
dapr_agents_oas_adapter/logging.py
dapr_agents_oas_adapter/py.typed
dapr_agents_oas_adapter/state.py
dapr_agents_oas_adapter/types.py
dapr_agents_oas_adapter/utils.py
dapr_agents_oas_adapter/validation.py
dapr_agents_oas_adapter-0.7.0.dist-info/licenses/LICENSE
dapr_agents_oas_adapter-0.7.0.dist-info/WHEEL
dapr_agents_oas_adapter-0.7.0.dist-info/METADATA
dapr_agents_oas_adapter-0.7.0.dist-info/RECORD
