Metadata-Version: 2.4
Name: dapr-agents-oas-adapter
Version: 0.7.0
Summary: Adapter library to make Dapr Agents compatible with Open Agent Spec
Author: Helton Dória
Author-email: Helton Dória <helton.doria@gmail.com>
License-Expression: Apache-2.0
License-File: LICENSE
Requires-Dist: pyagentspec>=25.4.1
Requires-Dist: dapr-agents>=0.10.5
Requires-Dist: dapr>=1.16.0
Requires-Dist: pydantic>=2.12.5
Requires-Dist: structlog>=24.1.0
Requires-Python: >=3.12
